[{"Country":"Switzerland","Date_confirmation":"2022-05-21","New_infected":1,"Total_infected":1},{"Country":"Switzerland","Date_confirmation":"2022-05-22","New_infected":0,"Total_infected":1},{"Country":"Switzerland","Date_confirmation":"2022-05-23","New_infected":0,"Total_infected":1},{"Country":"Switzerland","Date_confirmation":"2022-05-24","New_infected":1,"Total_infected":2},{"Country":"Switzerland","Date_confirmation":"2022-05-25","New_infected":0,"Total_infected":2},{"Country":"Switzerland","Date_confirmation":"2022-05-26","New_infected":1,"Total_infected":3},{"Country":"Switzerland","Date_confirmation":"2022-05-27","New_infected":1,"Total_infected":4},{"Country":"Switzerland","Date_confirmation":"2022-05-28","New_infected":0,"Total_infected":4},{"Country":"Switzerland","Date_confirmation":"2022-05-29","New_infected":0,"Total_infected":4},{"Country":"Switzerland","Date_confirmation":"2022-05-30","New_infected":0,"Total_infected":4},{"Country":"Switzerland","Date_confirmation":"2022-05-31","New_infected":0,"Total_infected":4},{"Country":"Switzerland","Date_confirmation":"2022-06-01","New_infected":0,"Total_infected":4},{"Country":"Switzerland","Date_confirmation":"2022-06-02","New_infected":2,"Total_infected":6},{"Country":"Switzerland","Date_confirmation":"2022-06-03","New_infected":2,"Total_infected":8},{"Country":"Switzerland","Date_confirmation":"2022-06-04","New_infected":0,"Total_infected":8},{"Country":"Switzerland","Date_confirmation":"2022-06-05","New_infected":0,"Total_infected":8},{"Country":"Switzerland","Date_confirmation":"2022-06-06","New_infected":0,"Total_infected":8},{"Country":"Switzerland","Date_confirmation":"2022-06-07","New_infected":2,"Total_infected":10},{"Country":"Switzerland","Date_confirmation":"2022-06-08","New_infected":2,"Total_infected":12},{"Country":"Switzerland","Date_confirmation":"2022-06-09","New_infected":0,"Total_infected":12},{"Country":"Switzerland","Date_confirmation":"2022-06-10","New_infected":2,"Total_infected":14},{"Country":"Switzerland","Date_confirmation":"2022-06-11","New_infected":0,"Total_infected":14},{"Country":"Switzerland","Date_confirmation":"2022-06-12","New_infected":0,"Total_infected":14},{"Country":"Switzerland","Date_confirmation":"2022-06-13","New_infected":5,"Total_infected":19},{"Country":"Switzerland","Date_confirmation":"2022-06-14","New_infected":1,"Total_infected":20},{"Country":"Switzerland","Date_confirmation":"2022-06-15","New_infected":8,"Total_infected":28},{"Country":"Switzerland","Date_confirmation":"2022-06-16","New_infected":2,"Total_infected":30},{"Country":"Switzerland","Date_confirmation":"2022-06-17","New_infected":1,"Total_infected":31},{"Country":"Switzerland","Date_confirmation":"2022-06-18","New_infected":0,"Total_infected":31},{"Country":"Switzerland","Date_confirmation":"2022-06-19","New_infected":0,"Total_infected":31},{"Country":"Switzerland","Date_confirmation":"2022-06-20","New_infected":9,"Total_infected":40},{"Country":"Switzerland","Date_confirmation":"2022-06-21","New_infected":1,"Total_infected":41},{"Country":"Switzerland","Date_confirmation":"2022-06-22","New_infected":5,"Total_infected":46},{"Country":"Switzerland","Date_confirmation":"2022-06-23","New_infected":6,"Total_infected":52},{"Country":"Switzerland","Date_confirmation":"2022-06-24","New_infected":3,"Total_infected":55},{"Country":"Switzerland","Date_confirmation":"2022-06-25","New_infected":0,"Total_infected":55},{"Country":"Switzerland","Date_confirmation":"2022-06-26","New_infected":0,"Total_infected":55},{"Country":"Switzerland","Date_confirmation":"2022-06-27","New_infected":13,"Total_infected":68},{"Country":"Switzerland","Date_confirmation":"2022-06-28","New_infected":4,"Total_infected":72},{"Country":"Switzerland","Date_confirmation":"2022-06-29","New_infected":9,"Total_infected":81},{"Country":"Switzerland","Date_confirmation":"2022-06-30","New_infected":2,"Total_infected":83},{"Country":"Switzerland","Date_confirmation":"2022-07-01","New_infected":0,"Total_infected":83}]